.DS_Store
pygments_xojo/__init__.py
pygments_xojo/lexer.py
pygments_xojo/styles.py
pygments_xojo-0.0.0.dist-info/DESCRIPTION.rst
pygments_xojo-0.0.0.dist-info/entry_points.txt
pygments_xojo-0.0.0.dist-info/METADATA
pygments_xojo-0.0.0.dist-info/metadata.json
pygments_xojo-0.0.0.dist-info/RECORD
pygments_xojo-0.0.0.dist-info/top_level.txt
pygments_xojo-0.0.0.dist-info/WHEEL
