Metadata-Version: 2.0
Name: pygments-xojo
Version: 0.0.0
Summary: Pygments highlighting for the Xojo language
Home-page: https://github.com/declaresub/pygments-xojo
Author: Charles Yeomans
Author-email: charles@declaresub.com
License: BSD License
Keywords: syntax highlighting xojo
Platform: any
Requires-Dist: pygments
